mytestpkgfranktcao/__init__.py
mytestpkgfranktcao/mytestpkg.py
mytestpkgfranktcao-0.1.3.dist-info/LICENSE
mytestpkgfranktcao-0.1.3.dist-info/METADATA
mytestpkgfranktcao-0.1.3.dist-info/WHEEL
mytestpkgfranktcao-0.1.3.dist-info/RECORD
