Metadata-Version: 2.1
Name: mytestpkgfranktcao
Version: 0.1.3
Summary: Test publishing on PyPI
License: MIT
Author: Frank Cao
Requires-Python: >=3.11,<4.0
Classifier: License :: OSI Approved :: MIT License
Classifier: Programming Language :: Python :: 3
Classifier: Programming Language :: Python :: 3.11
Classifier: Programming Language :: Python :: 3.12
